Metadata-Version: 2.4
Name: aircheck_test_model
Version: 1.1.3
Summary: AI models based on AIRCHECK data
Author: nabin bagale
License: MIT License
License-File: LICENSE
Requires-Dist: jinja2
Requires-Dist: pydantic~=2.0
Requires-Dist: pydantic-settings
Requires-Dist: typer
Requires-Dist: numpy
Requires-Dist: pandas
Requires-Dist: pympler
Requires-Dist: scikit-learn
Requires-Dist: gdown
Requires-Dist: catboost
Requires-Dist: scikit-optimize
Requires-Dist: lightgbm
Requires-Dist: rdkit
Requires-Dist: pyarrow
Requires-Dist: greenlet
Requires-Dist: pyyaml
Requires-Dist: tqdm
Provides-Extra: dev
Requires-Dist: build; extra == "dev"
Requires-Dist: dapperdata; extra == "dev"
Requires-Dist: glom; extra == "dev"
Requires-Dist: mypy; extra == "dev"
Requires-Dist: pytest; extra == "dev"
Requires-Dist: pytest-asyncio; extra == "dev"
Requires-Dist: pytest-cov; extra == "dev"
Requires-Dist: pytest-pretty; extra == "dev"
Requires-Dist: ruamel.yaml; extra == "dev"
Requires-Dist: ruff; extra == "dev"
Requires-Dist: toml-sort; extra == "dev"
Requires-Dist: uv; extra == "dev"
Requires-Dist: types-PyYAML; extra == "dev"
Requires-Dist: pandas-stubs; extra == "dev"
Requires-Dist: types-tqdm; extra == "dev"
Dynamic: license-file
